Metadata-Version: 2.1
Name: UniversalWrapper
Version: 2.4
Summary: UNKNOWN
Home-page: https://github.com/Basdbruijne/UniversalWrapper
Author: Bas de Bruijne
Author-email: basdbruijne@gmail.com
License: MIT
Keywords: wrapper,cli,subprocess
Platform: UNKNOWN
Classifier: Development Status :: 4 - Beta
Classifier: Intended Audience :: Developers
Classifier: Topic :: Software Development :: Build Tools
Classifier: License :: OSI Approved :: MIT License
Classifier: Programming Language :: Python :: 3.6
Classifier: Programming Language :: Python :: 3.7
Classifier: Programming Language :: Python :: 3.8
Classifier: Programming Language :: Python :: 3.9
Classifier: Programming Language :: Python :: 3.10
Classifier: Programming Language :: Python :: 3.11
License-File: LICENSE.txt
